snmp_diode/__init__.py
snmp_diode/discover.py
snmp_diode/entrypoint.py
snmp_diode/models.py
snmp_diode/sysobjectid.py
snmp_diode-0.0.6.dist-info/LICENSE.txt
snmp_diode-0.0.6.dist-info/METADATA
snmp_diode-0.0.6.dist-info/WHEEL
snmp_diode-0.0.6.dist-info/entry_points.txt
snmp_diode-0.0.6.dist-info/top_level.txt
snmp_diode-0.0.6.dist-info/RECORD
