Metadata-Version: 2.1
Name: snmp-diode
Version: 0.0.6
Summary: A SNMP Interface to NetBoxLabs Diode
Author-email: Renato Almeida de Oliveira <renato.almeida.oliveira@gmail.com>
Project-URL: Homepage, https://github.com/renatoalmeidaoliveira/snmp-diode/
Project-URL: Issues, https://github.com/renatoalmeidaoliveira/snmp-diode/issues
Classifier: Programming Language :: Python :: 3
Classifier: License :: OSI Approved :: MIT License
Classifier: Operating System :: OS Independent
Requires-Python: >=3.10
License-File: LICENSE.txt
Requires-Dist: netboxlabs-diode-sdk
Requires-Dist: pydantic
Requires-Dist: easysnmp
Requires-Dist: netaddr
